layer_viewer/__init__.py
layer_viewer/distinct_colors.py
layer_viewer/layer_ctrl_widget.py
layer_viewer/layer_view_widget.py
layer_viewer/layer_viewer.py
layer_viewer/layer_viewer_widget.py
layer_viewer/pixel_path.py
layer_viewer/settings_widget.py
layer_viewer/version.py
layer_viewer/cli/__init__.py
layer_viewer/cli/main.py
layer_viewer/layers/__init__.py
layer_viewer/layers/binary_object_layer.py
layer_viewer/layers/gray_image_layer.py
layer_viewer/layers/label_layer.py
layer_viewer/layers/layer_base.py
layer_viewer/layers/layer_controller.py
layer_viewer/layers/multi_channel_image_layer.py
layer_viewer/layers/object_layer.py
layer_viewer/layers/rgb_image_layer.py
layer_viewer/widgets/__init__.py
layer_viewer/widgets/fraction_selection_bar.py
layer_viewer/widgets/gradient_widget.py
layer_viewer/widgets/layer_view_settings.py
layer_viewer/widgets/toggle_eye.py
layer_viewer/widgets/icons/__init__.py
layer_viewer/widgets/ui/__init__.py
layer_viewer-0.1.1.dist-info/AUTHORS.rst
layer_viewer-0.1.1.dist-info/LICENSE.txt
layer_viewer-0.1.1.dist-info/METADATA
layer_viewer-0.1.1.dist-info/WHEEL
layer_viewer-0.1.1.dist-info/entry_points.txt
layer_viewer-0.1.1.dist-info/top_level.txt
layer_viewer-0.1.1.dist-info/RECORD
