Metadata-Version: 2.1
Name: layer-viewer
Version: 0.1.1
Summary: layer-viewer is a pyqt / pyqtgraph based layer viewer for 2d images
Home-page: https://github.com/DerThorsten/layer_viewer
Author: Thorsten Beier
Author-email: derthorstenbeier@gmail.com
License: UNKNOWN
Keywords: layer_viewer
Platform: UNKNOWN
Classifier: Development Status :: 2 - Pre-Alpha
Classifier: Intended Audience :: Developers
Classifier: Natural Language :: English
Classifier: Programming Language :: Python :: 3.6
Classifier: Programming Language :: Python :: 3.7
Classifier: Programming Language :: Python :: 3.8
Requires-Dist: click (>=6.0)
Requires-Dist: pyqtgraph
Requires-Dist: PyQt5
Requires-Dist: numpy
